{"version":1,"resource":"vscode-remote://ssh-remote%2B7b22686f73744e616d65223a22416e73692d636f6e227d/home/adminuser/ex03/app.py","entries":[{"id":"EkyT.py","timestamp":1731394379955},{"id":"eT1g.py","timestamp":1731395099316},{"id":"6tgv.py","timestamp":1731395230031},{"id":"BTu9.py","timestamp":1731395303185},{"id":"txCo.py","timestamp":1731396249147},{"id":"dh5T.py","source":"undoRedo.source","timestamp":1731396297833},{"id":"qiIp.py","timestamp":1731404290044},{"id":"o1Ob.py","source":"undoRedo.source","timestamp":1731404341380},{"id":"G5pa.py","source":"undoRedo.source","timestamp":1731404392312}]}